{
  "semesters": {
    "2026-1": {
      "lastUpdated": "2026-03-24T13:18:24.726Z",
      "yearSuffix": "2026-1",
      "data": {
        "A": 200,
        "B": 200,
        "C": 200,
        "D": 404,
        "E": 404,
        "F": 200,
        "G": 200,
        "H": 200,
        "I": 200,
        "J": 200,
        "K": 200,
        "L": 200,
        "X": 200
      }
    },
    "2026-2": {
      "lastUpdated": "2026-03-16T18:46:37.920Z",
      "data": {
        "A": 403,
        "B": 403,
        "C": 403,
        "D": 403,
        "E": 403,
        "F": 403,
        "G": 403,
        "H": 403,
        "I": 403,
        "J": 403,
        "K": 403,
        "L": 403
      }
    },
    "2025-2": {
      "lastUpdated": "2026-03-17T12:33:10.075Z",
      "yearSuffix": "2025-2",
      "data": {
        "A": 200,
        "B": 200,
        "C": 200,
        "D": 200,
        "E": 404,
        "F": 200,
        "G": 200,
        "H": 200,
        "I": 200,
        "J": 404,
        "K": 200,
        "L": 200,
        "X": 200
      }
    },
    "2025-1": {
      "lastUpdated": "2026-03-17T12:32:49.299Z",
      "yearSuffix": "2025-1",
      "data": {
        "A": 404,
        "B": 404,
        "C": 404,
        "D": 404,
        "E": 404,
        "F": 404,
        "G": 404,
        "H": 404,
        "I": 404,
        "J": 404,
        "K": 404,
        "L": 404,
        "X": 404
      }
    }
  }
}